errbot_backend_slackv3-0.3.2.dist-info/licenses/LICENSE
slackv3/__init__.py
slackv3/lib.py
slackv3/markdown.py
slackv3/person.py
slackv3/room.py
slackv3/slackv3.plug
slackv3/slackv3.py
errbot_backend_slackv3-0.3.2.dist-info/METADATA
errbot_backend_slackv3-0.3.2.dist-info/WHEEL
errbot_backend_slackv3-0.3.2.dist-info/entry_points.txt
errbot_backend_slackv3-0.3.2.dist-info/top_level.txt
errbot_backend_slackv3-0.3.2.dist-info/RECORD
