Metadata-Version: 2.4
Name: errbot-backend-slackv3
Version: 0.3.2
Summary: Errbot SlackV3 backend plugin
Author: Errbot
License-File: LICENSE
Requires-Dist: slack-sdk>=3.33.5
Requires-Dist: slackeventsapi>=3.0.0
Requires-Dist: aiohttp
Requires-Dist: markdown>=3.3.6
Dynamic: author
Dynamic: description
Dynamic: description-content-type
Dynamic: license-file
Dynamic: requires-dist
Dynamic: summary
